{
    "neoforge:conditions":  [
                                {
                                    "type":  "neoforge:mod_loaded",
                                    "modid":  "tfc_items"
                                }
                            ],
    "type":  "tfc:anvil",
    "ingredient":  {
                       "item":  "tfcm:metal/stamen/cobalt"
                   },
    "result":  {
                   "id":  "tfcm:metal/screw/cobalt",
                   "count":  5
               },
    "tier":  3,
    "rules":  [
                  "hit_any",
                  "hit_any",
                  "draw_last"
              ]
}

